{"current_level": 9, "total_coins": 171, "total_score": 302933, "unlocked_skins": ["default", "\u76ae\u80a41", "\u76ae\u80a42", "\u76ae\u80a43"], "selected_skin": "\u76ae\u80a41", "level_stats": {"0": {"coins": 3, "time": 4.34, "score": 5978}, "1": {"coins": 1, "time": 4.136, "score": 1993}, "2": {"coins": 7, "time": 9.95, "score": 13883}, "3": {"coins": 4, "time": 9.712, "score": 7935}, "4": {"coins": 5, "time": 13.348, "score": 9888}, "5": {"coins": 3, "time": 4.411, "score": 5977}, "6": {"coins": 6, "time": 11.664, "score": 11883}, "7": {"coins": 6, "time": 12.196, "score": 11878}, "8": {"coins": 5, "time": 11.834, "score": 9901}, "9": {"coins": 4, "time": 7.87, "score": 7947}, "0": {"coins": 3, "time": 5.147, "score": 5974}}}